webwindow.py
webwindow-1.2.1.dist-info/LICENSE
webwindow-1.2.1.dist-info/METADATA
webwindow-1.2.1.dist-info/WHEEL
webwindow-1.2.1.dist-info/top_level.txt
webwindow-1.2.1.dist-info/RECORD
