Metadata-Version: 2.1
Name: webwindow
Version: 1.2.1
Summary: WebGL Window
Home-page: https://github.com/szabolcsdombi/webwindow/
Author: Szabolcs Dombi
Author-email: szabolcs@szabolcsdombi.com
License: MIT
Project-URL: Source, https://github.com/szabolcsdombi/webwindow/
Project-URL: Bug Tracker, https://github.com/szabolcsdombi/webwindow/issues/
Keywords: WebGL,window
Platform: web
License-File: LICENSE
